able/__init__.py
able/advertisement.py
able/bluezdbus/__init__.py
able/bluezdbus/advertisement.py
able/bluezdbus/application.py
able/bluezdbus/characteristic.py
able/bluezdbus/configurator.py
able/bluezdbus/service.py
able/bluezdbus/utils.py
able/central.py
able/characteristic.py
able/corebluetooth/__init__.py
able/corebluetooth/advertisement.py
able/corebluetooth/application.py
able/corebluetooth/characteristic.py
able/corebluetooth/error.py
able/corebluetooth/peripheral_manager_delegate.py
able/corebluetooth/service.py
able/peripheral.py
able/plugins/ibeacon.py
able/service.py
able/utils.py
able-0.3.4.dist-info/WHEEL
able-0.3.4.dist-info/METADATA
able-0.3.4.dist-info/RECORD
