Metadata-Version: 2.1
Name: able
Version: 0.3.4
Summary: ABle (Allthenticate's Bluetooth Low Energy (Library)) is a platform agnostic python framework for communication with centrals as a BLE Peripheral with simple yet powerful 'BLE Sockets'
Home-page: https://allthenticate.com/
Keywords: BLE Peripheral,Bluetooth Low Energy
Author: Bernie Conrad
Author-email: bernie@allthenticate.com
Requires-Python: >=3.6.2,<4.0
Classifier: Development Status :: 3 - Alpha
Classifier: Framework :: AsyncIO
Classifier: Intended Audience :: Developers
Classifier: Operating System :: OS Independent
Classifier: Programming Language :: Python :: 3
Classifier: Programming Language :: Python :: 3.10
Classifier: Programming Language :: Python :: 3.7
Classifier: Programming Language :: Python :: 3.8
Classifier: Programming Language :: Python :: 3.9
Classifier: Topic :: Communications
Requires-Dist: dbus-next (>=0.2.2,<0.3.0); sys_platform == "linux"
Requires-Dist: pyobjc (>=7.3,<8.0); sys_platform == "darwin"
Project-URL: Documentation, http://docs.able.development.allthenticate.net.s3-website-us-west-1.amazonaws.com/
